[
  {
    "symbol": "RB0",
    "name": "螺纹钢",
    "close": 3168.0,
    "date": "2026-05-22",
    "n_days": 4163,
    "channels": {
      "short": {
        "r2": 0.005,
        "slope": 0.4451,
        "upper": 3281.24,
        "lower": 3163.22,
        "center": 3222.23,
        "width_pct": 3.7,
        "position_pct": 4.0,
        "zone": "下1/3 (接近下轨，加仓观察区)",
        "proj_d5_upper": 3283.46,
        "proj_d10_upper": 3285.69
      },
      "medium": {
        "r2": 0.665,
        "slope": 2.8104,
        "upper": 3283.64,
        "lower": 3178.24,
        "center": 3230.94,
        "width_pct": 3.3,
        "position_pct": -10.0,
        "zone": "下1/3 (接近下轨，加仓观察区)",
        "proj_d5_upper": 3297.69,
        "proj_d10_upper": 3311.74
      },
      "long": {
        "r2": 0.398,
        "slope": 0.8014,
        "upper": 3242.72,
        "lower": 3113.91,
        "center": 3178.31,
        "width_pct": 4.1,
        "position_pct": 42.0,
        "zone": "中1/3 (通道中枢，观望区)",
        "proj_d5_upper": 3246.73,
        "proj_d10_upper": 3250.73
      }
    },
    "patterns": {
      "short": {
        "count": 0,
        "items": []
      },
      "medium": {
        "count": 0,
        "items": []
      },
      "long": {
        "count": 0,
        "items": []
      }
    },
    "total_patterns": 0,
    "report_file": null,
    "report_size": 0
  },
  {
    "symbol": "HC0",
    "name": "热卷",
    "close": 3385.0,
    "date": "2026-05-22",
    "n_days": 2961,
    "channels": {
      "short": {
        "r2": 0.049,
        "slope": 1.588,
        "upper": 3511.45,
        "lower": 3384.12,
        "center": 3447.79,
        "width_pct": 3.7,
        "position_pct": 1.0,
        "zone": "下1/3 (接近下轨，加仓观察区)",
        "proj_d5_upper": 3519.39,
        "proj_d10_upper": 3527.33
      },
      "medium": {
        "r2": 0.782,
        "slope": 4.2221,
        "upper": 3514.84,
        "lower": 3396.89,
        "center": 3455.87,
        "width_pct": 3.4,
        "position_pct": -10.0,
        "zone": "下1/3 (接近下轨，加仓观察区)",
        "proj_d5_upper": 3535.95,
        "proj_d10_upper": 3557.06
      },
      "long": {
        "r2": 0.321,
        "slope": 0.8385,
        "upper": 3439.69,
        "lower": 3280.17,
        "center": 3359.93,
        "width_pct": 4.7,
        "position_pct": 66.0,
        "zone": "中1/3 (通道中枢，观望区)",
        "proj_d5_upper": 3443.88,
        "proj_d10_upper": 3448.07
      }
    },
    "patterns": {
      "short": {
        "count": 0,
        "items": []
      },
      "medium": {
        "count": 0,
        "items": []
      },
      "long": {
        "count": 1,
        "items": [
          {
            "type": "头肩",
            "pattern": "倒头肩底",
            "dir": "看涨",
            "target": 3484.0,
            "days": 50,
            "break": "2026-04-20"
          }
        ]
      }
    },
    "total_patterns": 1,
    "report_file": null,
    "report_size": 0
  },
  {
    "symbol": "I0",
    "name": "铁矿石",
    "close": 792.0,
    "date": "2026-05-22",
    "n_days": 3060,
    "channels": {
      "short": {
        "r2": 0.139,
        "slope": 0.8861,
        "upper": 829.43,
        "lower": 789.25,
        "center": 809.34,
        "width_pct": 5.0,
        "position_pct": 7.0,
        "zone": "下1/3 (接近下轨，加仓观察区)",
        "proj_d5_upper": 833.86,
        "proj_d10_upper": 838.29
      },
      "medium": {
        "r2": 0.155,
        "slope": 0.5354,
        "upper": 838.41,
        "lower": 772.46,
        "center": 805.44,
        "width_pct": 8.2,
        "position_pct": 30.0,
        "zone": "下1/3 (接近下轨，加仓观察区)",
        "proj_d5_upper": 841.09,
        "proj_d10_upper": 843.77
      },
      "long": {
        "r2": 0.043,
        "slope": 0.0963,
        "upper": 823.02,
        "lower": 763.64,
        "center": 793.33,
        "width_pct": 7.5,
        "position_pct": 48.0,
        "zone": "中1/3 (通道中枢，观望区)",
        "proj_d5_upper": 823.5,
        "proj_d10_upper": 823.98
      }
    },
    "patterns": {
      "short": {
        "count": 0,
        "items": []
      },
      "medium": {
        "count": 0,
        "items": []
      },
      "long": {
        "count": 0,
        "items": []
      }
    },
    "total_patterns": 0,
    "report_file": null,
    "report_size": 0
  },
  {
    "symbol": "J0",
    "name": "焦炭",
    "close": 1731.0,
    "date": "2026-05-22",
    "n_days": 3664,
    "channels": {
      "short": {
        "r2": 0.564,
        "slope": -4.8564,
        "upper": 1811.0,
        "lower": 1733.13,
        "center": 1772.06,
        "width_pct": 4.4,
        "position_pct": -3.0,
        "zone": "下1/3 (接近下轨，加仓观察区)",
        "proj_d5_upper": 1786.71,
        "proj_d10_upper": 1762.43
      },
      "medium": {
        "r2": 0.391,
        "slope": 2.5691,
        "upper": 1906.08,
        "lower": 1736.66,
        "center": 1821.37,
        "width_pct": 9.3,
        "position_pct": -3.0,
        "zone": "下1/3 (接近下轨，加仓观察区)",
        "proj_d5_upper": 1918.92,
        "proj_d10_upper": 1931.77
      },
      "long": {
        "r2": 0.106,
        "slope": -0.6278,
        "upper": 1832.62,
        "lower": 1594.63,
        "center": 1713.63,
        "width_pct": 13.9,
        "position_pct": 57.0,
        "zone": "中1/3 (通道中枢，观望区)",
        "proj_d5_upper": 1829.48,
        "proj_d10_upper": 1826.34
      }
    },
    "patterns": {
      "short": {
        "count": 0,
        "items": []
      },
      "medium": {
        "count": 0,
        "items": []
      },
      "long": {
        "count": 0,
        "items": []
      }
    },
    "total_patterns": 0,
    "report_file": null,
    "report_size": 0
  },
  {
    "symbol": "JM0",
    "name": "焦煤",
    "close": 1162.5,
    "date": "2026-05-22",
    "n_days": 3192,
    "channels": {
      "short": {
        "r2": 0.513,
        "slope": -4.8673,
        "upper": 1249.93,
        "lower": 1163.44,
        "center": 1206.69,
        "width_pct": 7.2,
        "position_pct": -1.0,
        "zone": "下1/3 (接近下轨，加仓观察区)",
        "proj_d5_upper": 1225.6,
        "proj_d10_upper": 1201.26
      },
      "medium": {
        "r2": 0.538,
        "slope": 3.7032,
        "upper": 1366.72,
        "lower": 1185.35,
        "center": 1276.03,
        "width_pct": 14.2,
        "position_pct": -13.0,
        "zone": "下1/3 (接近下轨，加仓观察区)",
        "proj_d5_upper": 1385.23,
        "proj_d10_upper": 1403.75
      },
      "long": {
        "r2": 0.001,
        "slope": -0.0656,
        "upper": 1287.05,
        "lower": 1006.84,
        "center": 1146.94,
        "width_pct": 24.4,
        "position_pct": 56.0,
        "zone": "中1/3 (通道中枢，观望区)",
        "proj_d5_upper": 1286.72,
        "proj_d10_upper": 1286.39
      }
    },
    "patterns": {
      "short": {
        "count": 0,
        "items": []
      },
      "medium": {
        "count": 0,
        "items": []
      },
      "long": {
        "count": 0,
        "items": []
      }
    },
    "total_patterns": 0,
    "report_file": null,
    "report_size": 0
  },
  {
    "symbol": "FG0",
    "name": "玻璃",
    "close": 1020.0,
    "date": "2026-05-22",
    "n_days": 3259,
    "channels": {
      "short": {
        "r2": 0.627,
        "slope": -3.0398,
        "upper": 1045.45,
        "lower": 1002.69,
        "center": 1024.07,
        "width_pct": 4.2,
        "position_pct": 40.0,
        "zone": "中1/3 (通道中枢，观望区)",
        "proj_d5_upper": 1030.26,
        "proj_d10_upper": 1015.06
      },
      "medium": {
        "r2": 0.775,
        "slope": -3.2258,
        "upper": 1063.93,
        "lower": 972.07,
        "center": 1018.0,
        "width_pct": 9.0,
        "position_pct": 52.0,
        "zone": "中1/3 (通道中枢，观望区)",
        "proj_d5_upper": 1047.8,
        "proj_d10_upper": 1031.67
      },
      "long": {
        "r2": 0.76,
        "slope": -1.8891,
        "upper": 1116.09,
        "lower": 977.07,
        "center": 1046.58,
        "width_pct": 13.3,
        "position_pct": 31.0,
        "zone": "下1/3 (接近下轨，加仓观察区)",
        "proj_d5_upper": 1106.65,
        "proj_d10_upper": 1097.2
      }
    },
    "patterns": {
      "short": {
        "count": 0,
        "items": []
      },
      "medium": {
        "count": 0,
        "items": []
      },
      "long": {
        "count": 2,
        "items": [
          {
            "type": "头肩",
            "pattern": "头肩顶",
            "dir": "看跌",
            "target": 972.64,
            "days": 32,
            "break": "2026-03-31"
          },
          {
            "type": "头肩",
            "pattern": "头肩顶",
            "dir": "看跌",
            "target": 972.64,
            "days": 46,
            "break": "2026-03-31"
          }
        ]
      }
    },
    "total_patterns": 2,
    "report_file": null,
    "report_size": 0
  },
  {
    "symbol": "UR0",
    "name": "尿素",
    "close": 1826.0,
    "date": "2026-05-22",
    "n_days": 1642,
    "channels": {
      "short": {
        "r2": 0.896,
        "slope": -13.3609,
        "upper": 1843.81,
        "lower": 1760.74,
        "center": 1802.27,
        "width_pct": 4.6,
        "position_pct": 79.0,
        "zone": "上1/3 (接近上轨，减仓观察区)",
        "proj_d5_upper": 1777.0,
        "proj_d10_upper": 1710.2
      },
      "medium": {
        "r2": 0.001,
        "slope": -0.1109,
        "upper": 1994.4,
        "lower": 1803.04,
        "center": 1898.72,
        "width_pct": 10.1,
        "position_pct": 12.0,
        "zone": "下1/3 (接近下轨，加仓观察区)",
        "proj_d5_upper": 1993.85,
        "proj_d10_upper": 1993.29
      },
      "long": {
        "r2": 0.583,
        "slope": 1.4826,
        "upper": 2038.23,
        "lower": 1874.14,
        "center": 1956.18,
        "width_pct": 8.4,
        "position_pct": -29.0,
        "zone": "下1/3 (接近下轨，加仓观察区)",
        "proj_d5_upper": 2045.64,
        "proj_d10_upper": 2053.05
      }
    },
    "patterns": {
      "short": {
        "count": 0,
        "items": []
      },
      "medium": {
        "count": 0,
        "items": []
      },
      "long": {
        "count": 0,
        "items": []
      }
    },
    "total_patterns": 0,
    "report_file": null,
    "report_size": 0
  },
  {
    "symbol": "SA0",
    "name": "纯碱",
    "close": 1181.0,
    "date": "2026-05-22",
    "n_days": 1563,
    "channels": {
      "short": {
        "r2": 0.822,
        "slope": -4.6398,
        "upper": 1200.65,
        "lower": 1161.29,
        "center": 1180.97,
        "width_pct": 3.3,
        "position_pct": 50.0,
        "zone": "中1/3 (通道中枢，观望区)",
        "proj_d5_upper": 1177.45,
        "proj_d10_upper": 1154.25
      },
      "medium": {
        "r2": 0.495,
        "slope": -1.7992,
        "upper": 1251.02,
        "lower": 1155.01,
        "center": 1203.02,
        "width_pct": 8.0,
        "position_pct": 27.0,
        "zone": "下1/3 (接近下轨，加仓观察区)",
        "proj_d5_upper": 1242.02,
        "proj_d10_upper": 1233.03
      },
      "long": {
        "r2": 0.117,
        "slope": -0.3132,
        "upper": 1295.38,
        "lower": 1182.86,
        "center": 1239.12,
        "width_pct": 9.1,
        "position_pct": -2.0,
        "zone": "下1/3 (接近下轨，加仓观察区)",
        "proj_d5_upper": 1293.81,
        "proj_d10_upper": 1292.25
      }
    },
    "patterns": {
      "short": {
        "count": 0,
        "items": []
      },
      "medium": {
        "count": 1,
        "items": [
          {
            "type": "头肩",
            "pattern": "头肩顶",
            "dir": "看跌",
            "target": 994.04,
            "days": 51,
            "break": "2026-05-15"
          }
        ]
      },
      "long": {
        "count": 1,
        "items": [
          {
            "type": "头肩",
            "pattern": "头肩顶",
            "dir": "看跌",
            "target": 1112.61,
            "days": 30,
            "break": "2026-05-08"
          }
        ]
      }
    },
    "total_patterns": 2,
    "report_file": null,
    "report_size": 0
  },
  {
    "symbol": "V0",
    "name": "PVC",
    "close": 4846.0,
    "date": "2026-05-22",
    "n_days": 4120,
    "channels": {
      "short": {
        "r2": 0.649,
        "slope": -19.1782,
        "upper": 5082.43,
        "lower": 4825.08,
        "center": 4953.76,
        "width_pct": 5.2,
        "position_pct": 8.0,
        "zone": "下1/3 (接近下轨，加仓观察区)",
        "proj_d5_upper": 4986.54,
        "proj_d10_upper": 4890.65
      },
      "medium": {
        "r2": 0.008,
        "slope": 1.5422,
        "upper": 5688.19,
        "lower": 4756.89,
        "center": 5222.54,
        "width_pct": 17.8,
        "position_pct": 10.0,
        "zone": "下1/3 (接近下轨，加仓观察区)",
        "proj_d5_upper": 5695.9,
        "proj_d10_upper": 5703.61
      },
      "long": {
        "r2": 0.454,
        "slope": 5.5831,
        "upper": 5643.9,
        "lower": 4843.02,
        "center": 5243.46,
        "width_pct": 15.3,
        "position_pct": 0.0,
        "zone": "下1/3 (接近下轨，加仓观察区)",
        "proj_d5_upper": 5671.81,
        "proj_d10_upper": 5699.73
      }
    },
    "patterns": {
      "short": {
        "count": 0,
        "items": []
      },
      "medium": {
        "count": 0,
        "items": []
      },
      "long": {
        "count": 0,
        "items": []
      }
    },
    "total_patterns": 0,
    "report_file": null,
    "report_size": 0
  },
  {
    "symbol": "M0",
    "name": "豆粕",
    "close": 2990.0,
    "date": "2026-05-22",
    "n_days": 5202,
    "channels": {
      "short": {
        "r2": 0.005,
        "slope": 0.2436,
        "upper": 3045.17,
        "lower": 2979.45,
        "center": 3012.31,
        "width_pct": 2.2,
        "position_pct": 16.0,
        "zone": "下1/3 (接近下轨，加仓观察区)",
        "proj_d5_upper": 3046.39,
        "proj_d10_upper": 3047.61
      },
      "medium": {
        "r2": 0.247,
        "slope": 2.0467,
        "upper": 3126.8,
        "lower": 2938.09,
        "center": 3032.44,
        "width_pct": 6.2,
        "position_pct": 28.0,
        "zone": "下1/3 (接近下轨，加仓观察区)",
        "proj_d5_upper": 3137.03,
        "proj_d10_upper": 3147.27
      },
      "long": {
        "r2": 0.628,
        "slope": 2.1128,
        "upper": 3113.12,
        "lower": 2900.33,
        "center": 3006.73,
        "width_pct": 7.1,
        "position_pct": 42.0,
        "zone": "中1/3 (通道中枢，观望区)",
        "proj_d5_upper": 3123.69,
        "proj_d10_upper": 3134.25
      }
    },
    "patterns": {
      "short": {
        "count": 0,
        "items": []
      },
      "medium": {
        "count": 0,
        "items": []
      },
      "long": {
        "count": 1,
        "items": [
          {
            "type": "头肩",
            "pattern": "倒头肩底",
            "dir": "看涨",
            "target": 2926.0,
            "days": 28,
            "break": "2026-02-25"
          }
        ]
      }
    },
    "total_patterns": 1,
    "report_file": null,
    "report_size": 0
  },
  {
    "symbol": "Y0",
    "name": "豆油",
    "close": 8505.0,
    "date": "2026-05-22",
    "n_days": 4945,
    "channels": {
      "short": {
        "r2": 0.133,
        "slope": -3.5669,
        "upper": 8605.0,
        "lower": 8439.23,
        "center": 8522.11,
        "width_pct": 1.9,
        "position_pct": 40.0,
        "zone": "中1/3 (通道中枢，观望区)",
        "proj_d5_upper": 8587.16,
        "proj_d10_upper": 8569.33
      },
      "medium": {
        "r2": 0.096,
        "slope": 2.4223,
        "upper": 8800.21,
        "lower": 8407.44,
        "center": 8603.83,
        "width_pct": 4.6,
        "position_pct": 25.0,
        "zone": "下1/3 (接近下轨，加仓观察区)",
        "proj_d5_upper": 8812.33,
        "proj_d10_upper": 8824.44
      },
      "long": {
        "r2": 0.398,
        "slope": 3.8197,
        "upper": 8860.26,
        "lower": 8246.0,
        "center": 8553.13,
        "width_pct": 7.2,
        "position_pct": 42.0,
        "zone": "中1/3 (通道中枢，观望区)",
        "proj_d5_upper": 8879.35,
        "proj_d10_upper": 8898.45
      }
    },
    "patterns": {
      "short": {
        "count": 0,
        "items": []
      },
      "medium": {
        "count": 0,
        "items": []
      },
      "long": {
        "count": 0,
        "items": []
      }
    },
    "total_patterns": 0,
    "report_file": null,
    "report_size": 0
  },
  {
    "symbol": "P0",
    "name": "棕榈油",
    "close": 9471.0,
    "date": "2026-05-22",
    "n_days": 4513,
    "channels": {
      "short": {
        "r2": 0.547,
        "slope": -18.0812,
        "upper": 9645.33,
        "lower": 9345.53,
        "center": 9495.43,
        "width_pct": 3.2,
        "position_pct": 42.0,
        "zone": "中1/3 (通道中枢，观望区)",
        "proj_d5_upper": 9554.92,
        "proj_d10_upper": 9464.51
      },
      "medium": {
        "r2": 0.175,
        "slope": 7.7412,
        "upper": 10245.93,
        "lower": 9358.9,
        "center": 9802.41,
        "width_pct": 9.0,
        "position_pct": 13.0,
        "zone": "下1/3 (接近下轨，加仓观察区)",
        "proj_d5_upper": 10284.64,
        "proj_d10_upper": 10323.35
      },
      "long": {
        "r2": 0.442,
        "slope": 7.4786,
        "upper": 10215.63,
        "lower": 9117.04,
        "center": 9666.34,
        "width_pct": 11.4,
        "position_pct": 32.0,
        "zone": "下1/3 (接近下轨，加仓观察区)",
        "proj_d5_upper": 10253.02,
        "proj_d10_upper": 10290.42
      }
    },
    "patterns": {
      "short": {
        "count": 0,
        "items": []
      },
      "medium": {
        "count": 0,
        "items": []
      },
      "long": {
        "count": 0,
        "items": []
      }
    },
    "total_patterns": 0,
    "report_file": null,
    "report_size": 0
  },
  {
    "symbol": "A0",
    "name": "豆一",
    "close": 4784.0,
    "date": "2026-05-22",
    "n_days": 5199,
    "channels": {
      "short": {
        "r2": 0.771,
        "slope": -13.5105,
        "upper": 4779.57,
        "lower": 4645.23,
        "center": 4712.4,
        "width_pct": 2.9,
        "position_pct": 103.0,
        "zone": "上1/3 (接近上轨，减仓观察区)",
        "proj_d5_upper": 4712.02,
        "proj_d10_upper": 4644.47
      },
      "medium": {
        "r2": 0.108,
        "slope": 2.2307,
        "upper": 5011.12,
        "lower": 4671.96,
        "center": 4841.54,
        "width_pct": 7.0,
        "position_pct": 33.0,
        "zone": "中1/3 (通道中枢，观望区)",
        "proj_d5_upper": 5022.27,
        "proj_d10_upper": 5033.43
      },
      "long": {
        "r2": 0.868,
        "slope": 6.7864,
        "upper": 5107.04,
        "lower": 4760.82,
        "center": 4933.93,
        "width_pct": 7.0,
        "position_pct": 7.0,
        "zone": "下1/3 (接近下轨，加仓观察区)",
        "proj_d5_upper": 5140.97,
        "proj_d10_upper": 5174.9
      }
    },
    "patterns": {
      "short": {
        "count": 0,
        "items": []
      },
      "medium": {
        "count": 0,
        "items": []
      },
      "long": {
        "count": 1,
        "items": [
          {
            "type": "头肩",
            "pattern": "倒头肩底",
            "dir": "看涨",
            "target": 4572.0,
            "days": 29,
            "break": "2026-01-22"
          }
        ]
      }
    },
    "total_patterns": 1,
    "report_file": null,
    "report_size": 0
  },
  {
    "symbol": "C0",
    "name": "玉米",
    "close": 2331.0,
    "date": "2026-05-22",
    "n_days": 5196,
    "channels": {
      "short": {
        "r2": 0.849,
        "slope": -5.6827,
        "upper": 2350.87,
        "lower": 2307.16,
        "center": 2329.01,
        "width_pct": 1.9,
        "position_pct": 55.0,
        "zone": "中1/3 (通道中枢，观望区)",
        "proj_d5_upper": 2322.46,
        "proj_d10_upper": 2294.04
      },
      "medium": {
        "r2": 0.002,
        "slope": 0.0771,
        "upper": 2423.15,
        "lower": 2338.36,
        "center": 2380.76,
        "width_pct": 3.6,
        "position_pct": -9.0,
        "zone": "下1/3 (接近下轨，加仓观察区)",
        "proj_d5_upper": 2423.54,
        "proj_d10_upper": 2423.92
      },
      "long": {
        "r2": 0.861,
        "slope": 2.0333,
        "upper": 2485.34,
        "lower": 2378.62,
        "center": 2431.98,
        "width_pct": 4.4,
        "position_pct": -45.0,
        "zone": "下1/3 (接近下轨，加仓观察区)",
        "proj_d5_upper": 2495.51,
        "proj_d10_upper": 2505.68
      }
    },
    "patterns": {
      "short": {
        "count": 0,
        "items": []
      },
      "medium": {
        "count": 0,
        "items": []
      },
      "long": {
        "count": 0,
        "items": []
      }
    },
    "total_patterns": 0,
    "report_file": null,
    "report_size": 0
  },
  {
    "symbol": "JD0",
    "name": "鸡蛋",
    "close": 4505.0,
    "date": "2026-05-22",
    "n_days": 3046,
    "channels": {
      "short": {
        "r2": 0.747,
        "slope": 12.2676,
        "upper": 4510.47,
        "lower": 4380.41,
        "center": 4445.44,
        "width_pct": 2.9,
        "position_pct": 96.0,
        "zone": "上1/3 (接近上轨，减仓观察区)",
        "proj_d5_upper": 4571.81,
        "proj_d10_upper": 4633.15
      },
      "medium": {
        "r2": 0.852,
        "slope": 7.7396,
        "upper": 4475.09,
        "lower": 4304.37,
        "center": 4389.73,
        "width_pct": 3.9,
        "position_pct": 118.0,
        "zone": "上1/3 (接近上轨，减仓观察区)",
        "proj_d5_upper": 4513.78,
        "proj_d10_upper": 4552.48
      },
      "long": {
        "r2": 0.186,
        "slope": 1.8533,
        "upper": 4431.74,
        "lower": 3925.27,
        "center": 4178.51,
        "width_pct": 12.1,
        "position_pct": 114.0,
        "zone": "上1/3 (接近上轨，减仓观察区)",
        "proj_d5_upper": 4441.01,
        "proj_d10_upper": 4450.27
      }
    },
    "patterns": {
      "short": {
        "count": 0,
        "items": []
      },
      "medium": {
        "count": 1,
        "items": [
          {
            "type": "三角形",
            "pattern": "上升三角形",
            "dir": "看涨",
            "target": 4696.99,
            "days": 20,
            "break": "2026-05-18"
          }
        ]
      },
      "long": {
        "count": 1,
        "items": [
          {
            "type": "头肩",
            "pattern": "倒头肩底",
            "dir": "看涨",
            "target": 4477.53,
            "days": 40,
            "break": "2026-04-13"
          }
        ]
      }
    },
    "total_patterns": 2,
    "report_file": null,
    "report_size": 0
  },
  {
    "symbol": "LH0",
    "name": "生猪",
    "close": 11190.0,
    "date": "2026-05-22",
    "n_days": 1298,
    "channels": {
      "short": {
        "r2": 0.583,
        "slope": -34.1203,
        "upper": 11061.42,
        "lower": 10535.29,
        "center": 10798.36,
        "width_pct": 4.9,
        "position_pct": 124.0,
        "zone": "上1/3 (接近上轨，减仓观察区)",
        "proj_d5_upper": 10890.82,
        "proj_d10_upper": 10720.22
      },
      "medium": {
        "r2": 0.577,
        "slope": -34.423,
        "upper": 11263.73,
        "lower": 9704.76,
        "center": 10484.24,
        "width_pct": 14.9,
        "position_pct": 95.0,
        "zone": "上1/3 (接近上轨，减仓观察区)",
        "proj_d5_upper": 11091.61,
        "proj_d10_upper": 10919.5
      },
      "long": {
        "r2": 0.741,
        "slope": -20.2885,
        "upper": 11814.27,
        "lower": 10244.11,
        "center": 11029.19,
        "width_pct": 14.2,
        "position_pct": 60.0,
        "zone": "中1/3 (通道中枢，观望区)",
        "proj_d5_upper": 11712.83,
        "proj_d10_upper": 11611.39
      }
    },
    "patterns": {
      "short": {
        "count": 0,
        "items": []
      },
      "medium": {
        "count": 1,
        "items": [
          {
            "type": "岛型反转",
            "pattern": "岛型顶",
            "dir": "看跌",
            "target": 12116.02,
            "days": 16,
            "break": "2026-02-24"
          }
        ]
      },
      "long": {
        "count": 1,
        "items": [
          {
            "type": "头肩",
            "pattern": "头肩顶",
            "dir": "看跌",
            "target": 11429.67,
            "days": 47,
            "break": "2026-03-16"
          }
        ]
      }
    },
    "total_patterns": 2,
    "report_file": null,
    "report_size": 0
  },
  {
    "symbol": "AP0",
    "name": "苹果",
    "close": 7560.0,
    "date": "2026-05-22",
    "n_days": 2033,
    "channels": {
      "short": {
        "r2": 0.473,
        "slope": -12.4955,
        "upper": 7593.7,
        "lower": 7352.99,
        "center": 7473.34,
        "width_pct": 3.2,
        "position_pct": 86.0,
        "zone": "上1/3 (接近上轨，减仓观察区)",
        "proj_d5_upper": 7531.22,
        "proj_d10_upper": 7468.74
      },
      "medium": {
        "r2": 0.74,
        "slope": -21.1788,
        "upper": 7807.31,
        "lower": 7143.82,
        "center": 7475.57,
        "width_pct": 8.9,
        "position_pct": 63.0,
        "zone": "中1/3 (通道中枢，观望区)",
        "proj_d5_upper": 7701.42,
        "proj_d10_upper": 7595.52
      },
      "long": {
        "r2": 0.121,
        "slope": 2.9525,
        "upper": 8670.79,
        "lower": 7630.35,
        "center": 8150.57,
        "width_pct": 12.8,
        "position_pct": -7.0,
        "zone": "下1/3 (接近下轨，加仓观察区)",
        "proj_d5_upper": 8685.56,
        "proj_d10_upper": 8700.32
      }
    },
    "patterns": {
      "short": {
        "count": 0,
        "items": []
      },
      "medium": {
        "count": 0,
        "items": []
      },
      "long": {
        "count": 1,
        "items": [
          {
            "type": "头肩",
            "pattern": "头肩顶",
            "dir": "看跌",
            "target": 6862.36,
            "days": 39,
            "break": "2026-05-18"
          }
        ]
      }
    },
    "total_patterns": 1,
    "report_file": null,
    "report_size": 0
  },
  {
    "symbol": "CF0",
    "name": "棉花",
    "close": 15895.0,
    "date": "2026-05-22",
    "n_days": 5200,
    "channels": {
      "short": {
        "r2": 0.269,
        "slope": -18.8045,
        "upper": 16410.21,
        "lower": 15845.5,
        "center": 16127.86,
        "width_pct": 3.5,
        "position_pct": 9.0,
        "zone": "下1/3 (接近下轨，加仓观察区)",
        "proj_d5_upper": 16316.19,
        "proj_d10_upper": 16222.17
      },
      "medium": {
        "r2": 0.673,
        "slope": 22.4739,
        "upper": 16784.04,
        "lower": 15955.42,
        "center": 16369.73,
        "width_pct": 5.1,
        "position_pct": -7.0,
        "zone": "下1/3 (接近下轨，加仓观察区)",
        "proj_d5_upper": 16896.41,
        "proj_d10_upper": 17008.78
      },
      "long": {
        "r2": 0.94,
        "slope": 21.6716,
        "upper": 16673.46,
        "lower": 15960.34,
        "center": 16316.9,
        "width_pct": 4.4,
        "position_pct": -9.0,
        "zone": "下1/3 (接近下轨，加仓观察区)",
        "proj_d5_upper": 16781.82,
        "proj_d10_upper": 16890.18
      }
    },
    "patterns": {
      "short": {
        "count": 0,
        "items": []
      },
      "medium": {
        "count": 0,
        "items": []
      },
      "long": {
        "count": 0,
        "items": []
      }
    },
    "total_patterns": 0,
    "report_file": null,
    "report_size": 0
  },
  {
    "symbol": "RM0",
    "name": "菜粕",
    "close": 2337.0,
    "date": "2026-05-22",
    "n_days": 3245,
    "channels": {
      "short": {
        "r2": 0.443,
        "slope": -3.2767,
        "upper": 2377.44,
        "lower": 2310.5,
        "center": 2343.97,
        "width_pct": 2.9,
        "position_pct": 40.0,
        "zone": "中1/3 (通道中枢，观望区)",
        "proj_d5_upper": 2361.06,
        "proj_d10_upper": 2344.67
      },
      "medium": {
        "r2": 0.0,
        "slope": -0.07,
        "upper": 2463.31,
        "lower": 2246.75,
        "center": 2355.03,
        "width_pct": 9.2,
        "position_pct": 42.0,
        "zone": "中1/3 (通道中枢，观望区)",
        "proj_d5_upper": 2462.96,
        "proj_d10_upper": 2462.61
      },
      "long": {
        "r2": 0.069,
        "slope": -0.4624,
        "upper": 2436.09,
        "lower": 2213.26,
        "center": 2324.68,
        "width_pct": 9.6,
        "position_pct": 56.0,
        "zone": "中1/3 (通道中枢，观望区)",
        "proj_d5_upper": 2433.78,
        "proj_d10_upper": 2431.47
      }
    },
    "patterns": {
      "short": {
        "count": 0,
        "items": []
      },
      "medium": {
        "count": 0,
        "items": []
      },
      "long": {
        "count": 0,
        "items": []
      }
    },
    "total_patterns": 0,
    "report_file": null,
    "report_size": 0
  },
  {
    "symbol": "SR0",
    "name": "白糖",
    "close": 5368.0,
    "date": "2026-05-22",
    "n_days": 4943,
    "channels": {
      "short": {
        "r2": 0.004,
        "slope": 0.415,
        "upper": 5490.82,
        "lower": 5369.26,
        "center": 5430.04,
        "width_pct": 2.2,
        "position_pct": -1.0,
        "zone": "下1/3 (接近下轨，加仓观察区)",
        "proj_d5_upper": 5492.9,
        "proj_d10_upper": 5494.97
      },
      "medium": {
        "r2": 0.141,
        "slope": 1.3476,
        "upper": 5516.05,
        "lower": 5340.63,
        "center": 5428.34,
        "width_pct": 3.2,
        "position_pct": 16.0,
        "zone": "下1/3 (接近下轨，加仓观察区)",
        "proj_d5_upper": 5522.79,
        "proj_d10_upper": 5529.53
      },
      "long": {
        "r2": 0.0,
        "slope": -0.0508,
        "upper": 5500.83,
        "lower": 5187.76,
        "center": 5344.29,
        "width_pct": 5.9,
        "position_pct": 58.0,
        "zone": "中1/3 (通道中枢，观望区)",
        "proj_d5_upper": 5500.57,
        "proj_d10_upper": 5500.32
      }
    },
    "patterns": {
      "short": {
        "count": 0,
        "items": []
      },
      "medium": {
        "count": 0,
        "items": []
      },
      "long": {
        "count": 1,
        "items": [
          {
            "type": "头肩",
            "pattern": "倒头肩底",
            "dir": "看涨",
            "target": 5484.0,
            "days": 29,
            "break": "2026-04-15"
          }
        ]
      }
    },
    "total_patterns": 1,
    "report_file": null,
    "report_size": 0
  },
  {
    "symbol": "CU0",
    "name": "沪铜",
    "close": 104870.0,
    "date": "2026-05-22",
    "n_days": 5199,
    "channels": {
      "short": {
        "r2": 0.338,
        "slope": 180.0451,
        "upper": 107943.06,
        "lower": 103343.8,
        "center": 105643.43,
        "width_pct": 4.4,
        "position_pct": 33.0,
        "zone": "中1/3 (通道中枢，观望区)",
        "proj_d5_upper": 108843.29,
        "proj_d10_upper": 109743.51
      },
      "medium": {
        "r2": 0.196,
        "slope": 90.3387,
        "upper": 108286.59,
        "lower": 98633.06,
        "center": 103459.83,
        "width_pct": 9.3,
        "position_pct": 65.0,
        "zone": "中1/3 (通道中枢，观望区)",
        "proj_d5_upper": 108738.28,
        "proj_d10_upper": 109189.97
      },
      "long": {
        "r2": 0.662,
        "slope": 130.4365,
        "upper": 112253.37,
        "lower": 100051.92,
        "center": 106152.65,
        "width_pct": 11.5,
        "position_pct": 39.0,
        "zone": "中1/3 (通道中枢，观望区)",
        "proj_d5_upper": 112905.56,
        "proj_d10_upper": 113557.74
      }
    },
    "patterns": {
      "short": {
        "count": 0,
        "items": []
      },
      "medium": {
        "count": 1,
        "items": [
          {
            "type": "头肩",
            "pattern": "倒头肩底",
            "dir": "看涨",
            "target": 117200.0,
            "days": 51,
            "break": "2026-05-22"
          }
        ]
      },
      "long": {
        "count": 0,
        "items": []
      }
    },
    "total_patterns": 1,
    "report_file": null,
    "report_size": 0
  },
  {
    "symbol": "AL0",
    "name": "沪铝",
    "close": 24505.0,
    "date": "2026-05-22",
    "n_days": 5199,
    "channels": {
      "short": {
        "r2": 0.455,
        "slope": -25.2444,
        "upper": 24618.51,
        "lower": 24114.35,
        "center": 24366.43,
        "width_pct": 2.1,
        "position_pct": 77.0,
        "zone": "上1/3 (接近上轨，减仓观察区)",
        "proj_d5_upper": 24492.29,
        "proj_d10_upper": 24366.06
      },
      "medium": {
        "r2": 0.034,
        "slope": 5.0214,
        "upper": 25449.84,
        "lower": 24037.42,
        "center": 24743.63,
        "width_pct": 5.7,
        "position_pct": 33.0,
        "zone": "中1/3 (通道中枢，观望区)",
        "proj_d5_upper": 25474.95,
        "proj_d10_upper": 25500.05
      },
      "long": {
        "r2": 0.792,
        "slope": 29.8723,
        "upper": 26551.31,
        "lower": 24546.6,
        "center": 25548.95,
        "width_pct": 7.8,
        "position_pct": -2.0,
        "zone": "下1/3 (接近下轨，加仓观察区)",
        "proj_d5_upper": 26700.67,
        "proj_d10_upper": 26850.03
      }
    },
    "patterns": {
      "short": {
        "count": 0,
        "items": []
      },
      "medium": {
        "count": 0,
        "items": []
      },
      "long": {
        "count": 0,
        "items": []
      }
    },
    "total_patterns": 0,
    "report_file": null,
    "report_size": 0
  },
  {
    "symbol": "ZN0",
    "name": "沪锌",
    "close": 24865.0,
    "date": "2026-05-22",
    "n_days": 4662,
    "channels": {
      "short": {
        "r2": 0.521,
        "slope": 44.3195,
        "upper": 25218.02,
        "lower": 24443.55,
        "center": 24830.79,
        "width_pct": 3.1,
        "position_pct": 54.0,
        "zone": "中1/3 (通道中枢，观望区)",
        "proj_d5_upper": 25439.62,
        "proj_d10_upper": 25661.22
      },
      "medium": {
        "r2": 0.04,
        "slope": 6.5875,
        "upper": 25091.96,
        "lower": 23388.87,
        "center": 24240.42,
        "width_pct": 7.0,
        "position_pct": 87.0,
        "zone": "上1/3 (接近上轨，减仓观察区)",
        "proj_d5_upper": 25124.9,
        "proj_d10_upper": 25157.84
      },
      "long": {
        "r2": 0.493,
        "slope": 15.3489,
        "upper": 25761.86,
        "lower": 23726.6,
        "center": 24744.23,
        "width_pct": 8.2,
        "position_pct": 56.0,
        "zone": "中1/3 (通道中枢，观望区)",
        "proj_d5_upper": 25838.6,
        "proj_d10_upper": 25915.35
      }
    },
    "patterns": {
      "short": {
        "count": 0,
        "items": []
      },
      "medium": {
        "count": 1,
        "items": [
          {
            "type": "头肩",
            "pattern": "倒头肩底",
            "dir": "看涨",
            "target": 26575.0,
            "days": 34,
            "break": "2026-05-13"
          }
        ]
      },
      "long": {
        "count": 0,
        "items": []
      }
    },
    "total_patterns": 1,
    "report_file": null,
    "report_size": 0
  },
  {
    "symbol": "NI0",
    "name": "沪镍",
    "close": 143330.0,
    "date": "2026-05-22",
    "n_days": 2711,
    "channels": {
      "short": {
        "r2": 0.09,
        "slope": -169.8271,
        "upper": 149576.01,
        "lower": 139710.28,
        "center": 144643.14,
        "width_pct": 6.8,
        "position_pct": 37.0,
        "zone": "中1/3 (通道中枢，观望区)",
        "proj_d5_upper": 148726.87,
        "proj_d10_upper": 147877.73
      },
      "medium": {
        "r2": 0.399,
        "slope": 197.0639,
        "upper": 152266.6,
        "lower": 139493.17,
        "center": 145879.89,
        "width_pct": 8.8,
        "position_pct": 30.0,
        "zone": "下1/3 (接近下轨，加仓观察区)",
        "proj_d5_upper": 153251.92,
        "proj_d10_upper": 154237.24
      },
      "long": {
        "r2": 0.65,
        "slope": 206.7183,
        "upper": 157268.99,
        "lower": 137440.96,
        "center": 147354.98,
        "width_pct": 13.5,
        "position_pct": 30.0,
        "zone": "下1/3 (接近下轨，加仓观察区)",
        "proj_d5_upper": 158302.58,
        "proj_d10_upper": 159336.17
      }
    },
    "patterns": {
      "short": {
        "count": 0,
        "items": []
      },
      "medium": {
        "count": 1,
        "items": [
          {
            "type": "头肩",
            "pattern": "倒头肩底",
            "dir": "看涨",
            "target": 150400.0,
            "days": 21,
            "break": "2026-04-15"
          }
        ]
      },
      "long": {
        "count": 0,
        "items": []
      }
    },
    "total_patterns": 1,
    "report_file": null,
    "report_size": 0
  },
  {
    "symbol": "AO0",
    "name": "氧化铝",
    "close": 2717.0,
    "date": "2026-05-22",
    "n_days": 707,
    "channels": {
      "short": {
        "r2": 0.696,
        "slope": -8.6752,
        "upper": 2772.58,
        "lower": 2667.99,
        "center": 2720.29,
        "width_pct": 3.8,
        "position_pct": 47.0,
        "zone": "中1/3 (通道中枢，观望区)",
        "proj_d5_upper": 2729.21,
        "proj_d10_upper": 2685.83
      },
      "medium": {
        "r2": 0.501,
        "slope": -6.1719,
        "upper": 2902.14,
        "lower": 2576.62,
        "center": 2739.38,
        "width_pct": 11.9,
        "position_pct": 43.0,
        "zone": "中1/3 (通道中枢，观望区)",
        "proj_d5_upper": 2871.28,
        "proj_d10_upper": 2840.42
      },
      "long": {
        "r2": 0.006,
        "slope": -0.2415,
        "upper": 3085.24,
        "lower": 2691.9,
        "center": 2888.57,
        "width_pct": 13.6,
        "position_pct": 6.0,
        "zone": "下1/3 (接近下轨，加仓观察区)",
        "proj_d5_upper": 3084.03,
        "proj_d10_upper": 3082.82
      }
    },
    "patterns": {
      "short": {
        "count": 0,
        "items": []
      },
      "medium": {
        "count": 0,
        "items": []
      },
      "long": {
        "count": 0,
        "items": []
      }
    },
    "total_patterns": 0,
    "report_file": null,
    "report_size": 0
  },
  {
    "symbol": "AU0",
    "name": "沪金",
    "close": 995.76,
    "date": "2026-05-22",
    "n_days": 4472,
    "channels": {
      "short": {
        "r2": 0.61,
        "slope": -2.4324,
        "upper": 1015.71,
        "lower": 980.27,
        "center": 997.99,
        "width_pct": 3.6,
        "position_pct": 44.0,
        "zone": "中1/3 (通道中枢，观望区)",
        "proj_d5_upper": 1003.55,
        "proj_d10_upper": 991.39
      },
      "medium": {
        "r2": 0.66,
        "slope": -4.16,
        "upper": 1040.95,
        "lower": 883.0,
        "center": 961.97,
        "width_pct": 16.4,
        "position_pct": 71.0,
        "zone": "上1/3 (接近上轨，减仓观察区)",
        "proj_d5_upper": 1020.15,
        "proj_d10_upper": 999.35
      },
      "long": {
        "r2": 0.001,
        "slope": -0.0524,
        "upper": 1223.54,
        "lower": 974.13,
        "center": 1098.84,
        "width_pct": 22.7,
        "position_pct": 9.0,
        "zone": "下1/3 (接近下轨，加仓观察区)",
        "proj_d5_upper": 1223.28,
        "proj_d10_upper": 1223.02
      }
    },
    "patterns": {
      "short": {
        "count": 0,
        "items": []
      },
      "medium": {
        "count": 0,
        "items": []
      },
      "long": {
        "count": 0,
        "items": []
      }
    },
    "total_patterns": 0,
    "report_file": null,
    "report_size": 0
  },
  {
    "symbol": "AG0",
    "name": "沪银",
    "close": 18681.0,
    "date": "2026-05-22",
    "n_days": 3413,
    "channels": {
      "short": {
        "r2": 0.013,
        "slope": 20.0128,
        "upper": 20952.22,
        "lower": 17810.92,
        "center": 19381.57,
        "width_pct": 16.2,
        "position_pct": 28.0,
        "zone": "下1/3 (接近下轨，加仓观察区)",
        "proj_d5_upper": 21052.29,
        "proj_d10_upper": 21152.35
      },
      "medium": {
        "r2": 0.043,
        "slope": -16.0725,
        "upper": 20677.33,
        "lower": 16690.59,
        "center": 18683.96,
        "width_pct": 21.3,
        "position_pct": 50.0,
        "zone": "中1/3 (通道中枢，观望区)",
        "proj_d5_upper": 20596.97,
        "proj_d10_upper": 20516.61
      },
      "long": {
        "r2": 0.615,
        "slope": 73.9432,
        "upper": 25827.16,
        "lower": 18175.08,
        "center": 22001.12,
        "width_pct": 34.8,
        "position_pct": 7.0,
        "zone": "下1/3 (接近下轨，加仓观察区)",
        "proj_d5_upper": 26196.88,
        "proj_d10_upper": 26566.59
      }
    },
    "patterns": {
      "short": {
        "count": 0,
        "items": []
      },
      "medium": {
        "count": 0,
        "items": []
      },
      "long": {
        "count": 0,
        "items": []
      }
    },
    "total_patterns": 0,
    "report_file": null,
    "report_size": 0
  },
  {
    "symbol": "SC0",
    "name": "原油",
    "close": 641.1,
    "date": "2026-05-22",
    "n_days": 1977,
    "channels": {
      "short": {
        "r2": 0.025,
        "slope": 0.5566,
        "upper": 688.35,
        "lower": 625.3,
        "center": 656.82,
        "width_pct": 9.6,
        "position_pct": 25.0,
        "zone": "下1/3 (接近下轨，加仓观察区)",
        "proj_d5_upper": 691.13,
        "proj_d10_upper": 693.92
      },
      "medium": {
        "r2": 0.155,
        "slope": 1.7386,
        "upper": 798.65,
        "lower": 584.03,
        "center": 691.34,
        "width_pct": 31.0,
        "position_pct": 27.0,
        "zone": "下1/3 (接近下轨，加仓观察区)",
        "proj_d5_upper": 807.34,
        "proj_d10_upper": 816.04
      },
      "long": {
        "r2": 0.651,
        "slope": 2.1933,
        "upper": 777.62,
        "lower": 567.63,
        "center": 672.62,
        "width_pct": 31.2,
        "position_pct": 35.0,
        "zone": "中1/3 (通道中枢，观望区)",
        "proj_d5_upper": 788.58,
        "proj_d10_upper": 799.55
      }
    },
    "patterns": {
      "short": {
        "count": 0,
        "items": []
      },
      "medium": {
        "count": 0,
        "items": []
      },
      "long": {
        "count": 0,
        "items": []
      }
    },
    "total_patterns": 0,
    "report_file": null,
    "report_size": 0
  },
  {
    "symbol": "TA0",
    "name": "PTA",
    "close": 6136.0,
    "date": "2026-05-22",
    "n_days": 4717,
    "channels": {
      "short": {
        "r2": 0.317,
        "slope": -16.0722,
        "upper": 6539.13,
        "lower": 6108.7,
        "center": 6323.91,
        "width_pct": 6.8,
        "position_pct": 6.0,
        "zone": "下1/3 (接近下轨，加仓观察区)",
        "proj_d5_upper": 6458.77,
        "proj_d10_upper": 6378.41
      },
      "medium": {
        "r2": 0.001,
        "slope": 0.5999,
        "upper": 6997.67,
        "lower": 6047.16,
        "center": 6522.41,
        "width_pct": 14.6,
        "position_pct": 9.0,
        "zone": "下1/3 (接近下轨，加仓观察区)",
        "proj_d5_upper": 7000.66,
        "proj_d10_upper": 7003.66
      },
      "long": {
        "r2": 0.823,
        "slope": 13.7412,
        "upper": 7240.3,
        "lower": 6407.4,
        "center": 6823.85,
        "width_pct": 12.2,
        "position_pct": -33.0,
        "zone": "下1/3 (接近下轨，加仓观察区)",
        "proj_d5_upper": 7309.0,
        "proj_d10_upper": 7377.71
      }
    },
    "patterns": {
      "short": {
        "count": 0,
        "items": []
      },
      "medium": {
        "count": 0,
        "items": []
      },
      "long": {
        "count": 0,
        "items": []
      }
    },
    "total_patterns": 0,
    "report_file": null,
    "report_size": 0
  },
  {
    "symbol": "MA0",
    "name": "甲醇",
    "close": 2927.0,
    "date": "2026-05-22",
    "n_days": 2763,
    "channels": {
      "short": {
        "r2": 0.011,
        "slope": 1.0594,
        "upper": 3033.5,
        "lower": 2850.33,
        "center": 2941.91,
        "width_pct": 6.2,
        "position_pct": 42.0,
        "zone": "中1/3 (通道中枢，观望区)",
        "proj_d5_upper": 3038.8,
        "proj_d10_upper": 3044.09
      },
      "medium": {
        "r2": 0.002,
        "slope": 0.5412,
        "upper": 3338.15,
        "lower": 2687.09,
        "center": 3012.62,
        "width_pct": 21.6,
        "position_pct": 37.0,
        "zone": "中1/3 (通道中枢，观望区)",
        "proj_d5_upper": 3340.86,
        "proj_d10_upper": 3343.56
      },
      "long": {
        "r2": 0.573,
        "slope": 5.2397,
        "upper": 3369.21,
        "lower": 2777.71,
        "center": 3073.46,
        "width_pct": 19.2,
        "position_pct": 25.0,
        "zone": "下1/3 (接近下轨，加仓观察区)",
        "proj_d5_upper": 3395.41,
        "proj_d10_upper": 3421.6
      }
    },
    "patterns": {
      "short": {
        "count": 0,
        "items": []
      },
      "medium": {
        "count": 0,
        "items": []
      },
      "long": {
        "count": 0,
        "items": []
      }
    },
    "total_patterns": 0,
    "report_file": null,
    "report_size": 0
  },
  {
    "symbol": "RU0",
    "name": "橡胶",
    "close": 17420.0,
    "date": "2026-05-22",
    "n_days": 5197,
    "channels": {
      "short": {
        "r2": 0.159,
        "slope": 20.8759,
        "upper": 18226.99,
        "lower": 17351.15,
        "center": 17789.07,
        "width_pct": 4.9,
        "position_pct": 8.0,
        "zone": "下1/3 (接近下轨，加仓观察区)",
        "proj_d5_upper": 18331.37,
        "proj_d10_upper": 18435.75
      },
      "medium": {
        "r2": 0.374,
        "slope": 17.6398,
        "upper": 18168.4,
        "lower": 16962.51,
        "center": 17565.46,
        "width_pct": 6.9,
        "position_pct": 38.0,
        "zone": "中1/3 (通道中枢，观望区)",
        "proj_d5_upper": 18256.6,
        "proj_d10_upper": 18344.8
      },
      "long": {
        "r2": 0.864,
        "slope": 19.1186,
        "upper": 18057.1,
        "lower": 17066.04,
        "center": 17561.57,
        "width_pct": 5.6,
        "position_pct": 36.0,
        "zone": "中1/3 (通道中枢，观望区)",
        "proj_d5_upper": 18152.69,
        "proj_d10_upper": 18248.29
      }
    },
    "patterns": {
      "short": {
        "count": 0,
        "items": []
      },
      "medium": {
        "count": 0,
        "items": []
      },
      "long": {
        "count": 0,
        "items": []
      }
    },
    "total_patterns": 0,
    "report_file": null,
    "report_size": 0
  },
  {
    "symbol": "BU0",
    "name": "沥青",
    "close": 4333.0,
    "date": "2026-05-22",
    "n_days": 3065,
    "channels": {
      "short": {
        "r2": 0.355,
        "slope": 11.8143,
        "upper": 4601.97,
        "lower": 4311.8,
        "center": 4456.89,
        "width_pct": 6.5,
        "position_pct": 7.0,
        "zone": "下1/3 (接近下轨，加仓观察区)",
        "proj_d5_upper": 4661.04,
        "proj_d10_upper": 4720.11
      },
      "medium": {
        "r2": 0.57,
        "slope": 18.9356,
        "upper": 5053.12,
        "lower": 4183.98,
        "center": 4618.55,
        "width_pct": 18.8,
        "position_pct": 17.0,
        "zone": "下1/3 (接近下轨，加仓观察区)",
        "proj_d5_upper": 5147.8,
        "proj_d10_upper": 5242.48
      },
      "long": {
        "r2": 0.643,
        "slope": 11.0896,
        "upper": 4783.75,
        "lower": 3704.03,
        "center": 4243.89,
        "width_pct": 25.4,
        "position_pct": 58.0,
        "zone": "中1/3 (通道中枢，观望区)",
        "proj_d5_upper": 4839.2,
        "proj_d10_upper": 4894.65
      }
    },
    "patterns": {
      "short": {
        "count": 0,
        "items": []
      },
      "medium": {
        "count": 0,
        "items": []
      },
      "long": {
        "count": 0,
        "items": []
      }
    },
    "total_patterns": 0,
    "report_file": null,
    "report_size": 0
  },
  {
    "symbol": "PG0",
    "name": "液化气",
    "close": 5948.0,
    "date": "2026-05-22",
    "n_days": 1489,
    "channels": {
      "short": {
        "r2": 0.511,
        "slope": 26.7331,
        "upper": 6399.17,
        "lower": 5921.86,
        "center": 6160.51,
        "width_pct": 7.7,
        "position_pct": 5.0,
        "zone": "下1/3 (接近下轨，加仓观察区)",
        "proj_d5_upper": 6532.84,
        "proj_d10_upper": 6666.5
      },
      "medium": {
        "r2": 0.408,
        "slope": 21.069,
        "upper": 6878.6,
        "lower": 5538.58,
        "center": 6208.59,
        "width_pct": 21.6,
        "position_pct": 31.0,
        "zone": "下1/3 (接近下轨，加仓观察区)",
        "proj_d5_upper": 6983.95,
        "proj_d10_upper": 7089.29
      },
      "long": {
        "r2": 0.677,
        "slope": 15.0333,
        "upper": 6529.6,
        "lower": 5171.36,
        "center": 5850.48,
        "width_pct": 23.2,
        "position_pct": 57.0,
        "zone": "中1/3 (通道中枢，观望区)",
        "proj_d5_upper": 6604.77,
        "proj_d10_upper": 6679.94
      }
    },
    "patterns": {
      "short": {
        "count": 0,
        "items": []
      },
      "medium": {
        "count": 0,
        "items": []
      },
      "long": {
        "count": 0,
        "items": []
      }
    },
    "total_patterns": 0,
    "report_file": null,
    "report_size": 0
  },
  {
    "symbol": "PP0",
    "name": "聚丙烯",
    "close": 8792.0,
    "date": "2026-05-22",
    "n_days": 2971,
    "channels": {
      "short": {
        "r2": 0.526,
        "slope": 24.7654,
        "upper": 9162.59,
        "lower": 8733.95,
        "center": 8948.27,
        "width_pct": 4.8,
        "position_pct": 14.0,
        "zone": "下1/3 (接近下轨，加仓观察区)",
        "proj_d5_upper": 9286.42,
        "proj_d10_upper": 9410.24
      },
      "medium": {
        "r2": 0.598,
        "slope": 26.6056,
        "upper": 9662.81,
        "lower": 8510.19,
        "center": 9086.5,
        "width_pct": 12.7,
        "position_pct": 24.0,
        "zone": "下1/3 (接近下轨，加仓观察区)",
        "proj_d5_upper": 9795.83,
        "proj_d10_upper": 9928.86
      },
      "long": {
        "r2": 0.723,
        "slope": 18.3007,
        "upper": 9376.58,
        "lower": 7893.84,
        "center": 8635.21,
        "width_pct": 17.2,
        "position_pct": 61.0,
        "zone": "中1/3 (通道中枢，观望区)",
        "proj_d5_upper": 9468.08,
        "proj_d10_upper": 9559.59
      }
    },
    "patterns": {
      "short": {
        "count": 0,
        "items": []
      },
      "medium": {
        "count": 0,
        "items": []
      },
      "long": {
        "count": 0,
        "items": []
      }
    },
    "total_patterns": 0,
    "report_file": null,
    "report_size": 0
  },
  {
    "symbol": "SH0",
    "name": "烧碱",
    "close": 2001.0,
    "date": "2026-05-22",
    "n_days": 645,
    "channels": {
      "short": {
        "r2": 0.434,
        "slope": -4.4383,
        "upper": 2061.08,
        "lower": 1968.69,
        "center": 2014.89,
        "width_pct": 4.6,
        "position_pct": 35.0,
        "zone": "中1/3 (通道中枢，观望区)",
        "proj_d5_upper": 2038.89,
        "proj_d10_upper": 2016.7
      },
      "medium": {
        "r2": 0.375,
        "slope": -6.5893,
        "upper": 2245.34,
        "lower": 1796.1,
        "center": 2020.72,
        "width_pct": 22.2,
        "position_pct": 46.0,
        "zone": "中1/3 (通道中枢，观望区)",
        "proj_d5_upper": 2212.39,
        "proj_d10_upper": 2179.44
      },
      "long": {
        "r2": 0.659,
        "slope": -3.9853,
        "upper": 2244.81,
        "lower": 1869.77,
        "center": 2057.29,
        "width_pct": 18.2,
        "position_pct": 35.0,
        "zone": "中1/3 (通道中枢，观望区)",
        "proj_d5_upper": 2224.88,
        "proj_d10_upper": 2204.96
      }
    },
    "patterns": {
      "short": {
        "count": 0,
        "items": []
      },
      "medium": {
        "count": 0,
        "items": []
      },
      "long": {
        "count": 0,
        "items": []
      }
    },
    "total_patterns": 0,
    "report_file": null,
    "report_size": 0
  },
  {
    "symbol": "LC0",
    "name": "碳酸锂",
    "close": 184460.0,
    "date": "2026-05-22",
    "n_days": 685,
    "channels": {
      "short": {
        "r2": 0.062,
        "slope": 412.812,
        "upper": 207154.22,
        "lower": 177969.21,
        "center": 192561.71,
        "width_pct": 15.2,
        "position_pct": 22.0,
        "zone": "下1/3 (接近下轨，加仓观察区)",
        "proj_d5_upper": 209218.28,
        "proj_d10_upper": 211282.34
      },
      "medium": {
        "r2": 0.447,
        "slope": 624.9476,
        "upper": 207722.18,
        "lower": 170960.7,
        "center": 189341.44,
        "width_pct": 19.4,
        "position_pct": 37.0,
        "zone": "中1/3 (通道中枢，观望区)",
        "proj_d5_upper": 210846.91,
        "proj_d10_upper": 213971.65
      },
      "long": {
        "r2": 0.731,
        "slope": 684.1991,
        "upper": 225346.92,
        "lower": 171135.31,
        "center": 198241.12,
        "width_pct": 27.3,
        "position_pct": 25.0,
        "zone": "下1/3 (接近下轨，加仓观察区)",
        "proj_d5_upper": 228767.92,
        "proj_d10_upper": 232188.91
      }
    },
    "patterns": {
      "short": {
        "count": 0,
        "items": []
      },
      "medium": {
        "count": 0,
        "items": []
      },
      "long": {
        "count": 0,
        "items": []
      }
    },
    "total_patterns": 0,
    "report_file": null,
    "report_size": 0
  },
  {
    "symbol": "SI0",
    "name": "工业硅",
    "close": 8440.0,
    "date": "2026-05-22",
    "n_days": 824,
    "channels": {
      "short": {
        "r2": 0.188,
        "slope": -15.703,
        "upper": 8840.87,
        "lower": 8245.27,
        "center": 8543.07,
        "width_pct": 7.0,
        "position_pct": 33.0,
        "zone": "下1/3 (接近下轨，加仓观察区)",
        "proj_d5_upper": 8762.36,
        "proj_d10_upper": 8683.84
      },
      "medium": {
        "r2": 0.112,
        "slope": 3.9153,
        "upper": 8962.63,
        "lower": 8379.7,
        "center": 8671.17,
        "width_pct": 6.7,
        "position_pct": 10.0,
        "zone": "下1/3 (接近下轨，加仓观察区)",
        "proj_d5_upper": 8982.21,
        "proj_d10_upper": 9001.78
      },
      "long": {
        "r2": 0.351,
        "slope": -3.7543,
        "upper": 8781.47,
        "lower": 8113.25,
        "center": 8447.36,
        "width_pct": 7.9,
        "position_pct": 49.0,
        "zone": "中1/3 (通道中枢，观望区)",
        "proj_d5_upper": 8762.7,
        "proj_d10_upper": 8743.93
      }
    },
    "patterns": {
      "short": {
        "count": 0,
        "items": []
      },
      "medium": {
        "count": 0,
        "items": []
      },
      "long": {
        "count": 0,
        "items": []
      }
    },
    "total_patterns": 0,
    "report_file": null,
    "report_size": 0
  },
  {
    "symbol": "T0",
    "name": "10年国债",
    "close": 108.93,
    "date": "2026-05-22",
    "n_days": 2265,
    "channels": {
      "short": {
        "r2": 0.478,
        "slope": 0.0211,
        "upper": 109.17,
        "lower": 108.77,
        "center": 108.97,
        "width_pct": 0.4,
        "position_pct": 40.0,
        "zone": "中1/3 (通道中枢，观望区)",
        "proj_d5_upper": 109.27,
        "proj_d10_upper": 109.38
      },
      "medium": {
        "r2": 0.478,
        "slope": 0.0102,
        "upper": 109.08,
        "lower": 108.52,
        "center": 108.8,
        "width_pct": 0.5,
        "position_pct": 73.0,
        "zone": "上1/3 (接近上轨，减仓观察区)",
        "proj_d5_upper": 109.13,
        "proj_d10_upper": 109.18
      },
      "long": {
        "r2": 0.253,
        "slope": 0.0035,
        "upper": 108.96,
        "lower": 108.18,
        "center": 108.57,
        "width_pct": 0.7,
        "position_pct": 96.0,
        "zone": "上1/3 (接近上轨，减仓观察区)",
        "proj_d5_upper": 108.98,
        "proj_d10_upper": 108.99
      }
    },
    "patterns": {
      "short": {
        "count": 0,
        "items": []
      },
      "medium": {
        "count": 1,
        "items": [
          {
            "type": "头肩",
            "pattern": "倒头肩底",
            "dir": "看涨",
            "target": 109.09,
            "days": 40,
            "break": "2026-05-07"
          }
        ]
      },
      "long": {
        "count": 1,
        "items": [
          {
            "type": "头肩",
            "pattern": "倒头肩底",
            "dir": "看涨",
            "target": 109.48,
            "days": 64,
            "break": "2026-04-28"
          }
        ]
      }
    },
    "total_patterns": 2,
    "report_file": null,
    "report_size": 0
  },
  {
    "symbol": "TF0",
    "name": "5年国债",
    "close": 106.455,
    "date": "2026-05-22",
    "n_days": 2265,
    "channels": {
      "short": {
        "r2": 0.656,
        "slope": 0.0181,
        "upper": 106.6,
        "lower": 106.36,
        "center": 106.48,
        "width_pct": 0.2,
        "position_pct": 40.0,
        "zone": "中1/3 (通道中枢，观望区)",
        "proj_d5_upper": 106.69,
        "proj_d10_upper": 106.78
      },
      "medium": {
        "r2": 0.564,
        "slope": 0.0073,
        "upper": 106.5,
        "lower": 106.17,
        "center": 106.34,
        "width_pct": 0.3,
        "position_pct": 85.0,
        "zone": "上1/3 (接近上轨，减仓观察区)",
        "proj_d5_upper": 106.54,
        "proj_d10_upper": 106.58
      },
      "long": {
        "r2": 0.495,
        "slope": 0.0033,
        "upper": 106.42,
        "lower": 105.98,
        "center": 106.2,
        "width_pct": 0.4,
        "position_pct": 108.0,
        "zone": "上1/3 (接近上轨，减仓观察区)",
        "proj_d5_upper": 106.43,
        "proj_d10_upper": 106.45
      }
    },
    "patterns": {
      "short": {
        "count": 0,
        "items": []
      },
      "medium": {
        "count": 0,
        "items": []
      },
      "long": {
        "count": 1,
        "items": [
          {
            "type": "头肩",
            "pattern": "倒头肩底",
            "dir": "看涨",
            "target": 106.96,
            "days": 64,
            "break": "2026-05-11"
          }
        ]
      }
    },
    "total_patterns": 1,
    "report_file": null,
    "report_size": 0
  },
  {
    "symbol": "TS0",
    "name": "2年国债",
    "close": 102.652,
    "date": "2026-05-22",
    "n_days": 1879,
    "channels": {
      "short": {
        "r2": 0.408,
        "slope": 0.0051,
        "upper": 102.7,
        "lower": 102.59,
        "center": 102.64,
        "width_pct": 0.1,
        "position_pct": 59.0,
        "zone": "中1/3 (通道中枢，观望区)",
        "proj_d5_upper": 102.72,
        "proj_d10_upper": 102.75
      },
      "medium": {
        "r2": 0.71,
        "slope": 0.0029,
        "upper": 102.67,
        "lower": 102.57,
        "center": 102.62,
        "width_pct": 0.1,
        "position_pct": 86.0,
        "zone": "上1/3 (接近上轨，减仓观察区)",
        "proj_d5_upper": 102.68,
        "proj_d10_upper": 102.69
      },
      "long": {
        "r2": 0.432,
        "slope": 0.0012,
        "upper": 102.64,
        "lower": 102.47,
        "center": 102.56,
        "width_pct": 0.2,
        "position_pct": 105.0,
        "zone": "上1/3 (接近上轨，减仓观察区)",
        "proj_d5_upper": 102.65,
        "proj_d10_upper": 102.66
      }
    },
    "patterns": {
      "short": {
        "count": 0,
        "items": []
      },
      "medium": {
        "count": 0,
        "items": []
      },
      "long": {
        "count": 1,
        "items": [
          {
            "type": "头肩",
            "pattern": "倒头肩底",
            "dir": "看涨",
            "target": 102.72,
            "days": 41,
            "break": "2026-04-14"
          }
        ]
      }
    },
    "total_patterns": 1,
    "report_file": null,
    "report_size": 0
  },
  {
    "symbol": "TL0",
    "name": "30年国债",
    "close": 112.98,
    "date": "2026-05-22",
    "n_days": 745,
    "channels": {
      "short": {
        "r2": 0.181,
        "slope": -0.0332,
        "upper": 113.32,
        "lower": 112.04,
        "center": 112.68,
        "width_pct": 1.1,
        "position_pct": 73.0,
        "zone": "上1/3 (接近上轨，减仓观察区)",
        "proj_d5_upper": 113.15,
        "proj_d10_upper": 112.99
      },
      "medium": {
        "r2": 0.249,
        "slope": 0.0259,
        "upper": 114.24,
        "lower": 111.87,
        "center": 113.06,
        "width_pct": 2.1,
        "position_pct": 47.0,
        "zone": "中1/3 (通道中枢，观望区)",
        "proj_d5_upper": 114.37,
        "proj_d10_upper": 114.5
      },
      "long": {
        "r2": 0.348,
        "slope": -0.0228,
        "upper": 113.39,
        "lower": 109.32,
        "center": 111.35,
        "width_pct": 3.7,
        "position_pct": 90.0,
        "zone": "上1/3 (接近上轨，减仓观察区)",
        "proj_d5_upper": 113.28,
        "proj_d10_upper": 113.16
      }
    },
    "patterns": {
      "short": {
        "count": 0,
        "items": []
      },
      "medium": {
        "count": 0,
        "items": []
      },
      "long": {
        "count": 1,
        "items": [
          {
            "type": "头肩",
            "pattern": "倒头肩底",
            "dir": "看涨",
            "target": 115.33,
            "days": 35,
            "break": "2026-05-22"
          }
        ]
      }
    },
    "total_patterns": 1,
    "report_file": null,
    "report_size": 0
  }
]