{
  "code": "AO",
  "name": "氧化铝",
  "symbol": "AO0",
  "data_range": "2023-2026",
  "total_rows": 700,
  "n_years": 4,
  "all_month_mean": 0.15,
  "best_month": 5,
  "best_month_mean": 4.17,
  "worst_month": 1,
  "worst_month_mean": -9.89,
  "monthly": [
    {
      "mean": -9.89,
      "median": -4.68,
      "std": 10.22,
      "win_rate": 0.0,
      "max_up": -0.82,
      "max_down": -24.16,
      "n_years": 3
    },
    {
      "mean": -2.42,
      "median": -0.83,
      "std": 3.09,
      "win_rate": 33.3,
      "max_up": 0.31,
      "max_down": -6.74,
      "n_years": 3
    },
    {
      "mean": -2.55,
      "median": 1.76,
      "std": 6.95,
      "win_rate": 66.7,
      "max_up": 2.95,
      "max_down": -12.36,
      "n_years": 3
    },
    {
      "mean": 2.42,
      "median": 0.89,
      "std": 8.45,
      "win_rate": 66.7,
      "max_up": 13.46,
      "max_down": -7.08,
      "n_years": 3
    },
    {
      "mean": 4.17,
      "median": 5.85,
      "std": 4.07,
      "win_rate": 66.7,
      "max_up": 8.1,
      "max_down": -1.44,
      "n_years": 3
    },
    {
      "mean": -1.09,
      "median": -1.49,
      "std": 3.19,
      "win_rate": 33.3,
      "max_up": 3.0,
      "max_down": -4.78,
      "n_years": 3
    },
    {
      "mean": 1.99,
      "median": 2.56,
      "std": 5.37,
      "win_rate": 66.7,
      "max_up": 8.27,
      "max_down": -4.85,
      "n_years": 3
    },
    {
      "mean": 1.94,
      "median": 3.15,
      "std": 5.82,
      "win_rate": 66.7,
      "max_up": 8.39,
      "max_down": -5.71,
      "n_years": 3
    },
    {
      "mean": 1.14,
      "median": 2.82,
      "std": 4.79,
      "win_rate": 66.7,
      "max_up": 5.98,
      "max_down": -5.38,
      "n_years": 3
    },
    {
      "mean": 3.09,
      "median": -1.17,
      "std": 7.52,
      "win_rate": 33.3,
      "max_up": 13.65,
      "max_down": -3.22,
      "n_years": 3
    },
    {
      "mean": 0.26,
      "median": -2.99,
      "std": 4.79,
      "win_rate": 33.3,
      "max_up": 7.03,
      "max_down": -3.25,
      "n_years": 3
    },
    {
      "mean": 2.79,
      "median": 2.85,
      "std": 8.92,
      "win_rate": 66.7,
      "max_up": 13.68,
      "max_down": -8.17,
      "n_years": 3
    }
  ],
  "rallies": [
    {
      "avg_gain": 5.6,
      "avg_days": 3.0,
      "avg_start_day": 3.5,
      "timing": {
        "上旬": 1,
        "中旬": 1,
        "下旬": 0
      },
      "n_episodes": 2
    },
    {
      "avg_gain": 4.5,
      "avg_days": 7.3,
      "avg_start_day": 5.3,
      "timing": {
        "上旬": 1,
        "中旬": 2,
        "下旬": 0
      },
      "n_episodes": 3
    },
    {
      "avg_gain": 6.9,
      "avg_days": 11.0,
      "avg_start_day": 6.3,
      "timing": {
        "上旬": 2,
        "中旬": 0,
        "下旬": 1
      },
      "n_episodes": 3
    },
    {
      "avg_gain": 9.5,
      "avg_days": 10.7,
      "avg_start_day": 6.3,
      "timing": {
        "上旬": 2,
        "中旬": 1,
        "下旬": 0
      },
      "n_episodes": 3
    },
    {
      "avg_gain": 17.2,
      "avg_days": 9.0,
      "avg_start_day": 4.5,
      "timing": {
        "上旬": 1,
        "中旬": 1,
        "下旬": 0
      },
      "n_episodes": 2
    },
    {
      "avg_gain": 3.8,
      "avg_days": 7.3,
      "avg_start_day": 7.0,
      "timing": {
        "上旬": 1,
        "中旬": 2,
        "下旬": 0
      },
      "n_episodes": 3
    },
    {
      "avg_gain": 7.4,
      "avg_days": 9.3,
      "avg_start_day": 8.0,
      "timing": {
        "上旬": 1,
        "中旬": 1,
        "下旬": 1
      },
      "n_episodes": 3
    },
    {
      "avg_gain": 6.9,
      "avg_days": 10.0,
      "avg_start_day": 5.7,
      "timing": {
        "上旬": 2,
        "中旬": 0,
        "下旬": 1
      },
      "n_episodes": 3
    },
    {
      "avg_gain": 5.3,
      "avg_days": 6.3,
      "avg_start_day": 8.3,
      "timing": {
        "上旬": 1,
        "中旬": 1,
        "下旬": 1
      },
      "n_episodes": 3
    },
    {
      "avg_gain": 9.1,
      "avg_days": 9.0,
      "avg_start_day": 3.3,
      "timing": {
        "上旬": 2,
        "中旬": 1,
        "下旬": 0
      },
      "n_episodes": 3
    },
    {
      "avg_gain": 5.1,
      "avg_days": 9.0,
      "avg_start_day": 4.3,
      "timing": {
        "上旬": 2,
        "中旬": 1,
        "下旬": 0
      },
      "n_episodes": 3
    },
    {
      "avg_gain": 11.5,
      "avg_days": 11.7,
      "avg_start_day": 10.0,
      "timing": {
        "上旬": 0,
        "中旬": 2,
        "下旬": 1
      },
      "n_episodes": 3
    }
  ],
  "updated": "2026-05-14 09:47"
}