{
  "code": "RB",
  "name": "螺纹钢",
  "symbol": "RB0",
  "data_range": "2009-2026",
  "total_rows": 4156,
  "n_years": 18,
  "all_month_mean": 0.27,
  "best_month": 7,
  "best_month_mean": 3.32,
  "worst_month": 5,
  "worst_month_mean": -3.3,
  "monthly": [
    {
      "mean": 1.97,
      "median": 1.05,
      "std": 5.35,
      "win_rate": 52.9,
      "max_up": 14.28,
      "max_down": -4.93,
      "n_years": 17
    },
    {
      "mean": 0.2,
      "median": -1.52,
      "std": 4.05,
      "win_rate": 47.1,
      "max_up": 9.45,
      "max_down": -4.54,
      "n_years": 17
    },
    {
      "mean": -0.93,
      "median": -0.8,
      "std": 4.8,
      "win_rate": 38.9,
      "max_up": 7.45,
      "max_down": -10.53,
      "n_years": 18
    },
    {
      "mean": 1.84,
      "median": -0.67,
      "std": 7.81,
      "win_rate": 44.4,
      "max_up": 25.14,
      "max_down": -12.04,
      "n_years": 18
    },
    {
      "mean": -3.3,
      "median": -2.79,
      "std": 5.4,
      "win_rate": 27.8,
      "max_up": 5.73,
      "max_down": -19.69,
      "n_years": 18
    },
    {
      "mean": 1.77,
      "median": 1.66,
      "std": 6.44,
      "win_rate": 58.8,
      "max_up": 18.33,
      "max_down": -8.47,
      "n_years": 17
    },
    {
      "mean": 3.32,
      "median": 3.47,
      "std": 7.47,
      "win_rate": 64.7,
      "max_up": 20.94,
      "max_down": -8.14,
      "n_years": 17
    },
    {
      "mean": -2.71,
      "median": -2.48,
      "std": 5.16,
      "win_rate": 29.4,
      "max_up": 10.11,
      "max_down": -13.75,
      "n_years": 17
    },
    {
      "mean": -2.35,
      "median": -3.33,
      "std": 6.37,
      "win_rate": 29.4,
      "max_up": 9.97,
      "max_down": -13.97,
      "n_years": 17
    },
    {
      "mean": -1.14,
      "median": 0.25,
      "std": 7.33,
      "win_rate": 52.9,
      "max_up": 16.07,
      "max_down": -19.55,
      "n_years": 17
    },
    {
      "mean": 1.29,
      "median": 0.88,
      "std": 6.63,
      "win_rate": 58.8,
      "max_up": 11.91,
      "max_down": -12.75,
      "n_years": 17
    },
    {
      "mean": 3.31,
      "median": 2.76,
      "std": 5.36,
      "win_rate": 70.6,
      "max_up": 14.5,
      "max_down": -4.98,
      "n_years": 17
    }
  ],
  "rallies": [
    {
      "avg_gain": 5.3,
      "avg_days": 9.5,
      "avg_start_day": 6.3,
      "timing": {
        "上旬": 8,
        "中旬": 4,
        "下旬": 4
      },
      "n_episodes": 16
    },
    {
      "avg_gain": 5.8,
      "avg_days": 8.5,
      "avg_start_day": 6.2,
      "timing": {
        "上旬": 7,
        "中旬": 4,
        "下旬": 3
      },
      "n_episodes": 14
    },
    {
      "avg_gain": 5.0,
      "avg_days": 8.3,
      "avg_start_day": 8.2,
      "timing": {
        "上旬": 7,
        "中旬": 5,
        "下旬": 5
      },
      "n_episodes": 17
    },
    {
      "avg_gain": 7.5,
      "avg_days": 9.9,
      "avg_start_day": 3.5,
      "timing": {
        "上旬": 11,
        "中旬": 4,
        "下旬": 0
      },
      "n_episodes": 15
    },
    {
      "avg_gain": 5.1,
      "avg_days": 6.3,
      "avg_start_day": 8.9,
      "timing": {
        "上旬": 5,
        "中旬": 4,
        "下旬": 6
      },
      "n_episodes": 15
    },
    {
      "avg_gain": 6.3,
      "avg_days": 10.4,
      "avg_start_day": 5.8,
      "timing": {
        "上旬": 9,
        "中旬": 3,
        "下旬": 2
      },
      "n_episodes": 14
    },
    {
      "avg_gain": 7.4,
      "avg_days": 11.4,
      "avg_start_day": 5.7,
      "timing": {
        "上旬": 9,
        "中旬": 5,
        "下旬": 3
      },
      "n_episodes": 17
    },
    {
      "avg_gain": 5.4,
      "avg_days": 7.8,
      "avg_start_day": 7.6,
      "timing": {
        "上旬": 5,
        "中旬": 4,
        "下旬": 4
      },
      "n_episodes": 13
    },
    {
      "avg_gain": 5.9,
      "avg_days": 6.8,
      "avg_start_day": 6.5,
      "timing": {
        "上旬": 7,
        "中旬": 3,
        "下旬": 3
      },
      "n_episodes": 13
    },
    {
      "avg_gain": 5.6,
      "avg_days": 8.2,
      "avg_start_day": 5.7,
      "timing": {
        "上旬": 7,
        "中旬": 5,
        "下旬": 2
      },
      "n_episodes": 14
    },
    {
      "avg_gain": 7.0,
      "avg_days": 9.5,
      "avg_start_day": 7.3,
      "timing": {
        "上旬": 7,
        "中旬": 2,
        "下旬": 6
      },
      "n_episodes": 15
    },
    {
      "avg_gain": 6.4,
      "avg_days": 10.5,
      "avg_start_day": 5.9,
      "timing": {
        "上旬": 8,
        "中旬": 7,
        "下旬": 1
      },
      "n_episodes": 16
    }
  ],
  "updated": "2026-05-14 12:59",
  "summary": "**季节性明显**：有明显的多空季节切换。基于2009-2026共18年数据，月均涨跌+0.27%。\n\n🌞 **做多窗口**：6-7月，累计均值+5.09%，胜率稳定。\n\n🌧️ **回避窗口**：8-10月，累计均值-6.20%，做多风险较大。\n\n⭐ **最佳单月**：7月（均值+3.32%，胜率65%）  |  ⚠️ **最差单月**：5月（均值-3.30%，胜率28%）\n\n📊 **高胜率月**：12月(胜率71%)、7月(胜率65%)、6月(胜率59%)\n\n🚀 **最强波段月**：4月，15次历史波段，平均涨幅+7.5%，持续9.9天。"
}